{
    "BOX ENDURANCE-59N": {
        "ETB": "27-08-2025 15:00:00",
        "MANIFEST": "2025-02046",
        "ATA": "---",
        "ETD": "28-08-2025 04:00:00",
        "ATD": "---",
        "SERVICE": "ZCX NB",
        "DRY CUTOFF": "26-08-2025 14:00:00",
        "REEFER CUTOFF": "26-08-2025 22:00:00"
    },
    "CONTSHIP CUP-43N": {
        "ETB": "03-09-2025 14:00:00",
        "MANIFEST": "2025-02143",
        "ATA": "---",
        "ETD": "04-09-2025 04:00:00",
        "ATD": "---",
        "SERVICE": "ZCX NB",
        "DRY CUTOFF": "02-09-2025 14:00:00",
        "REEFER CUTOFF": "02-09-2025 22:00:00"
    }
}